PComponentA.py
PComponentA-0.0.3.dist-info/METADATA
PComponentA-0.0.3.dist-info/WHEEL
PComponentA-0.0.3.dist-info/entry_points.txt
PComponentA-0.0.3.dist-info/top_level.txt
PComponentA-0.0.3.dist-info/RECORD
