Metadata-Version: 2.1
Name: PComponentA
Version: 0.0.3
Summary: A tool for principal component analysis
Home-page: https://github.com/Ri-Shitetsu/Decom
Author: Ri_Shitetsu
Author-email: s2122089@stu.musashino-u.ac.jp
License: UNKNOWN
Project-URL: Bug Tracker, https://github.com/Ri-Shitetsu/Decom
Platform: UNKNOWN
Classifier: Programming Language :: Python :: 3
Classifier: License :: OSI Approved :: MIT License
Classifier: Operating System :: OS Independent
Requires-Python: >=3.7
